tensorflow_s3/__init__.py
tensorflow_s3/libtensorflow_s3.so
tensorflow_s3-0.0.4.dist-info/WHEEL
tensorflow_s3-0.0.4.dist-info/METADATA
tensorflow_s3-0.0.4.dist-info/RECORD
