Metadata-Version: 2.1
Name: tensorflow_s3
Author: Ukjae Jeong
Author-email: jeongukjae@gmail.com
Summary: Test package to extend TensorFlow with S3 support
Requires-Dist: tensorflow>=2.19,<2.20
Version: 0.0.4
